secret_server/__init__.py
secret_server/commands.py
secret_server/config.py
secret_server/sdk_client.py
secret_server_sdk_client-1.0.dist-info/METADATA
secret_server_sdk_client-1.0.dist-info/RECORD
secret_server_sdk_client-1.0.dist-info/WHEEL
secret_server_sdk_client-1.0.dist-info/top_level.txt
