Metadata-Version: 2.1
Name: secret-server-sdk-client
Version: 1.0
Summary: Thycotic python client that uses the Thycotic SDK to get secrets from secret server
Home-page: https://github.com/thycotic/secret-server-python
Author: Paulo Dorado
Author-email: support@thycotic.com
License: UNKNOWN
Platform: UNKNOWN
Classifier: Programming Language :: Python :: 3
Classifier: License :: OSI Approved :: MIT License
Classifier: Operating System :: OS Independent
